durango/AGENTS.md
durango/__init__.py
durango/config_manager.py
durango/exceptions.py
durango/settings.py
durango/config/AGENTS.md
durango/config/__init__.py
durango/sources/AGENTS.md
durango/sources/__init__.py
durango/sources/env.py
durango/sources/file.py
durango/sources/user.py
durango/utils/AGENTS.md
durango/utils/__init__.py
durango/utils/merge.py
durango/utils/paths.py
durango-0.1.3.dist-info/METADATA
durango-0.1.3.dist-info/WHEEL
durango-0.1.3.dist-info/licenses/LICENSE
durango-0.1.3.dist-info/RECORD
