Metadata-Version: 2.4
Name: durango
Version: 0.1.3
Summary: Flexible layered configuration management built on Pydantic Settings.
Project-URL: Homepage, https://github.com/durango-dev/durango
Project-URL: Documentation, https://durango.dev/docs
Project-URL: Issues, https://github.com/durango-dev/durango/issues
Author-email: Durango Maintainers <dev@durango.dev>
License: MIT
License-File: LICENSE
Keywords: configuration,pydantic,settings,toml,yaml
Classifier: Development Status :: 3 - Alpha
Classifier: Intended Audience :: Developers
Classifier: License :: OSI Approved :: MIT License
Classifier: Programming Language :: Python :: 3
Classifier: Programming Language :: Python :: 3.9
Classifier: Programming Language :: Python :: 3.10
Classifier: Programming Language :: Python :: 3.11
Classifier: Programming Language :: Python :: 3.12
Classifier: Topic :: Software Development :: Libraries :: Application Frameworks
Classifier: Topic :: Utilities
Requires-Python: >=3.9
Requires-Dist: invoke>=2.2.1
Requires-Dist: mkdocs-click>=0.9.0
Requires-Dist: mkdocs-shadcn>=0.9.7
Requires-Dist: pydantic-settings>=2.2
Requires-Dist: pydantic>=2.7
Requires-Dist: python-dateutil>=2.9
Requires-Dist: ruamel-yaml>=0.17
Requires-Dist: tomli>=2.0.1; python_version < '3.11'
Provides-Extra: dev
Requires-Dist: mypy>=1.10; extra == 'dev'
Requires-Dist: pre-commit>=3.7; extra == 'dev'
Requires-Dist: pytest-cov>=4.1; extra == 'dev'
Requires-Dist: pytest>=7.4; extra == 'dev'
Requires-Dist: ruff>=0.4; extra == 'dev'
Provides-Extra: docs
Requires-Dist: mkdocs-click>=0.9; extra == 'docs'
Requires-Dist: mkdocs-shadcn>=0.9.7; extra == 'docs'
Requires-Dist: mkdocs>=1.5; extra == 'docs'
Requires-Dist: mkdocstrings[python]>=0.24; extra == 'docs'
